flask_rest_error_handling/__init__.py
flask_rest_error_handling-3.1.0.dist-info/LICENSE
flask_rest_error_handling-3.1.0.dist-info/METADATA
flask_rest_error_handling-3.1.0.dist-info/WHEEL
flask_rest_error_handling-3.1.0.dist-info/top_level.txt
flask_rest_error_handling-3.1.0.dist-info/RECORD
